Workbook

Sheet Assumptions
A1: Parameter | B1: Year 0 | C1: Year 1 | D1: Year 2 | E1: Year 3 | F1: Year 4 | G1: Year 5 | H1: Year 6 | I1: Year 7 | J1: Year 8 | K1: Year 9 | L1: Year 10
A2: Price per Unit
A3: Volume (Customers / Units)
A4: Revenue Growth %
A5: Variable Cost % of Revenue
A6: Fixed Costs
A7: Tax Rate
A8: Capex
A9: Depreciation (Years)
A10: Debtor Days
A11: Creditor Days
A12: Inventory Days
A13: Interest Rate on Debt
... A15: Debt Drawdown

Sheet Revenue
B1: Year 0 | C1: Year 1 | D1: Year 2 | E1: Year 3 | F1: Year 4 | G1: Year 5 | H1: Year 6 | I1: Year 7 | J1: Year 8 | K1: Year 9 | L1: Year 10
A2: Revenue | B2: =Assumptions!B2*Assumptions!B3 -> 0 | C2: =Revenue!B2*(1+Assumptions!C3) -> 0 | D2: =Revenue!C2*(1+Assumptions!D3) -> 0 | E2: =Revenue!D2*(1+Assumptions!E3) -> 0 | F2: =Revenue!E2*(1+Assumptions!F3) -> 0 | G2: =Revenue!F2*(1+Assumptions!G3) -> 0 | H2: =Revenue!G2*(1+Assumptions!H3) -> 0 | I2: =Revenue!H2*(1+Assumptions!I3) -> 0 | J2: =Revenue!I2*(1+Assumptions!J3) -> 0 | ... L2: =Revenue!K2*(1+Assumptions!L3) -> 0

Sheet Operating Costs
B1: Year 0 | C1: Year 1 | D1: Year 2 | E1: Year 3 | F1: Year 4 | G1: Year 5 | H1: Year 6 | I1: Year 7 | J1: Year 8 | K1: Year 9 | L1: Year 10
A2: Variable Costs | B2: =Revenue!B2*Assumptions!B4 -> 0 | C2: =Revenue!C2*Assumptions!C4 -> 0 | D2: =Revenue!D2*Assumptions!D4 -> 0 | E2: =Revenue!E2*Assumptions!E4 -> 0 | F2: =Revenue!F2*Assumptions!F4 -> 0 | G2: =Revenue!G2*Assumptions!G4 -> 0 | H2: =Revenue!H2*Assumptions!H4 -> 0 | I2: =Revenue!I2*Assumptions!I4 -> 0 | ... L2: =Revenue!L2*Assumptions!L4 -> 0
A3: Fixed Costs | B3: =Assumptions!B5 -> 0 | C3: =Assumptions!C5 -> 0 | D3: =Assumptions!D5 -> 0 | E3: =Assumptions!E5 -> 0 | F3: =Assumptions!F5 -> 0 | G3: =Assumptions!G5 -> 0 | H3: =Assumptions!H5 -> 0 | I3: =Assumptions!I5 -> 0 | ... L3: =Assumptions!L5 -> 0

Sheet P&L
B1: Year 0 | C1: Year 1 | D1: Year 2 | E1: Year 3 | F1: Year 4 | G1: Year 5 | H1: Year 6 | I1: Year 7 | J1: Year 8 | K1: Year 9 | L1: Year 10
A2: Revenue | B2: =Revenue!B2 -> 0 | C2: =Revenue!C2 -> 0 | D2: =Revenue!D2 -> 0 | E2: =Revenue!E2 -> 0 | F2: =Revenue!F2 -> 0 | G2: =Revenue!G2 -> 0 | H2: =Revenue!H2 -> 0 | I2: =Revenue!I2 -> 0 | ... L2: =Revenue!L2 -> 0
A3: Total Costs | B3: =SUM('Operating Costs'!B2:B3) -> 0 | C3: =SUM('Operating Costs'!C2:C3) -> 0 | D3: =SUM('Operating Costs'!D2:D3) -> 0 | E3: =SUM('Operating Costs'!E2:E3) -> 0 | F3: =SUM('Operating Costs'!F2:F3) -> 0 | G3: =SUM('Operating Costs'!G2:G3) -> 0 | H3: =SUM('Operating Costs'!H2:H3) -> 0 | I3: =SUM('Operating Costs'!I2:I3) -> 0 | ... L3: =SUM('Operating Costs'!L2:L3) -> 0
A4: EBITDA | B4: =B2-B3 -> 0 | C4: =C2-C3 -> 0 | D4: =D2-D3 -> 0 | E4: =E2-E3 -> 0 | F4: =F2-F3 -> 0 | G4: =G2-G3 -> 0 | H4: =H2-H3 -> 0 | I4: =I2-I3 -> 0 | ... L4: =L2-L3 -> 0
A5: Depreciation | B5: =Assumptions!B7/Assumptions!B8 -> #DIV/0! | C5: =Assumptions!C7/Assumptions!C8 -> #DIV/0! | D5: =Assumptions!D7/Assumptions!D8 -> #DIV/0! | E5: =Assumptions!E7/Assumptions!E8 -> #DIV/0! | F5: =Assumptions!F7/Assumptions!F8 -> #DIV/0! | G5: =Assumptions!G7/Assumptions!G8 -> #DIV/0! | H5: =Assumptions!H7/Assumptions!H8 -> #DIV/0! | I5: =Assumptions!I7/Assumptions!I8 -> #DIV/0! | ... L5: =Assumptions!L7/Assumptions!L8 -> #DIV/0!
A6: EBIT | B6: =B4-B5 -> #DIV/0! | C6: =C4-C5 -> #DIV/0! | D6: =D4-D5 -> #DIV/0! | E6: =E4-E5 -> #DIV/0! | F6: =F4-F5 -> #DIV/0! | G6: =G4-G5 -> #DIV/0! | H6: =H4-H5 -> #DIV/0! | I6: =I4-I5 -> #DIV/0! | ... L6: =L4-L5 -> #DIV/0!
A7: Interest | B7: =[1]Debt!B3*Assumptions!B12 -> #REF! | C7: =[1]Debt!C3*Assumptions!C12 -> #REF! | D7: =[1]Debt!D3*Assumptions!D12 -> #REF! | E7: =[1]Debt!E3*Assumptions!E12 -> #REF! | F7: =[1]Debt!F3*Assumptions!F12 -> #REF! | G7: =[1]Debt!G3*Assumptions!G12 -> #REF! | H7: =[1]Debt!H3*Assumptions!H12 -> #REF! | I7: =[1]Debt!I3*Assumptions!I12 -> #REF! | ... L7: =[1]Debt!L3*Assumptions!L12 -> #REF!
A8: PBT | B8: =B6-B7 -> #DIV/0! | C8: =C6-C7 -> #DIV/0! | D8: =D6-D7 -> #DIV/0! | E8: =E6-E7 -> #DIV/0! | F8: =F6-F7 -> #DIV/0! | G8: =G6-G7 -> #DIV/0! | H8: =H6-H7 -> #DIV/0! | I8: =I6-I7 -> #DIV/0! | ... L8: =L6-L7 -> #DIV/0!
A9: Tax | B9: =B8*Assumptions!B6 -> #DIV/0! | C9: =C8*Assumptions!C6 -> #DIV/0! | D9: =D8*Assumptions!D6 -> #DIV/0! | E9: =E8*Assumptions!E6 -> #DIV/0! | F9: =F8*Assumptions!F6 -> #DIV/0! | G9: =G8*Assumptions!G6 -> #DIV/0! | H9: =H8*Assumptions!H6 -> #DIV/0! | I9: =I8*Assumptions!I6 -> #DIV/0! | ... L9: =L8*Assumptions!L6 -> #DIV/0!
A10: PAT | B10: =B8-B9 -> #DIV/0! | C10: =C8-C9 -> #DIV/0! | D10: =D8-D9 -> #DIV/0! | E10: =E8-E9 -> #DIV/0! | F10: =F8-F9 -> #DIV/0! | G10: =G8-G9 -> #DIV/0! | H10: =H8-H9 -> #DIV/0! | I10: =I8-I9 -> #DIV/0! | ... L10: =L8-L9 -> #DIV/0!

Sheet Balance Sheet
B1: Year 0 | C1: Year 1 | D1: Year 2 | E1: Year 3 | F1: Year 4 | G1: Year 5 | H1: Year 6 | I1: Year 7 | J1: Year 8 | K1: Year 9 | L1: Year 10
A2: Fixed Assets | B2: =SUM('Cash Flow'!B6) -> 0 | C2: =SUM('Cash Flow'!C6) -> 0 | D2: =SUM('Cash Flow'!D6) -> 0 | E2: =SUM('Cash Flow'!E6) -> 0 | F2: =SUM('Cash Flow'!F6) -> 0 | G2: =SUM('Cash Flow'!G6) -> 0 | H2: =SUM('Cash Flow'!H6) -> 0 | I2: =SUM('Cash Flow'!I6) -> 0 | ... L2: =SUM('Cash Flow'!L6) -> 0
A3: Working Capital | B3: 0 | C3: 0 | D3: 0 | E3: 0 | F3: 0 | G3: 0 | H3: 0 | I3: 0 | J3: 0 | K3: 0 | L3: 0
A4: Cash | B4: ='Cash Flow'!B9 -> #DIV/0! | C4: ='Cash Flow'!C9 -> #DIV/0! | D4: ='Cash Flow'!D9 -> #DIV/0! | E4: ='Cash Flow'!E9 -> #DIV/0! | F4: ='Cash Flow'!F9 -> #DIV/0! | G4: ='Cash Flow'!G9 -> #DIV/0! | H4: ='Cash Flow'!H9 -> #DIV/0! | I4: ='Cash Flow'!I9 -> #DIV/0! | ... L4: ='Cash Flow'!L9 -> #DIV/0!
A5: Total Assets | B5: =SUM(B2:B4) -> #DIV/0! | C5: =SUM(C2:C4) -> #DIV/0! | D5: =SUM(D2:D4) -> #DIV/0! | E5: =SUM(E2:E4) -> #DIV/0! | F5: =SUM(F2:F4) -> #DIV/0! | G5: =SUM(G2:G4) -> #DIV/0! | H5: =SUM(H2:H4) -> #DIV/0! | I5: =SUM(I2:I4) -> #DIV/0! | ... L5: =SUM(L2:L4) -> #DIV/0!
A6: Equity | B6: =Assumptions!B13 -> 0 | C6: =Assumptions!C13 -> 0 | D6: =Assumptions!D13 -> 0 | E6: =Assumptions!E13 -> 0 | F6: =Assumptions!F13 -> 0 | G6: =Assumptions!G13 -> 0 | H6: =Assumptions!H13 -> 0 | I6: =Assumptions!I13 -> 0 | ... L6: =Assumptions!L13 -> 0
A7: Debt | B7: =Assumptions!B14 -> 0 | C7: =Assumptions!C14 -> 0 | D7: =Assumptions!D14 -> 0 | E7: =Assumptions!E14 -> 0 | F7: =Assumptions!F14 -> 0 | G7: =Assumptions!G14 -> 0 | H7: =Assumptions!H14 -> 0 | I7: =Assumptions!I14 -> 0 | ... L7: =Assumptions!L14 -> 0
A8: Retained Earnings | B8: ='P&L'!B10 -> #DIV/0! | C8: ='P&L'!C10 -> #DIV/0! | D8: ='P&L'!D10 -> #DIV/0! | E8: ='P&L'!E10 -> #DIV/0! | F8: ='P&L'!F10 -> #DIV/0! | G8: ='P&L'!G10 -> #DIV/0! | H8: ='P&L'!H10 -> #DIV/0! | I8: ='P&L'!I10 -> #DIV/0! | ... L8: ='P&L'!L10 -> #DIV/0!
A9: Total Liabilities | B9: =SUM(B6:B8) -> #DIV/0! | C9: =SUM(C6:C8) -> #DIV/0! | D9: =SUM(D6:D8) -> #DIV/0! | E9: =SUM(E6:E8) -> #DIV/0! | F9: =SUM(F6:F8) -> #DIV/0! | G9: =SUM(G6:G8) -> #DIV/0! | H9: =SUM(H6:H8) -> #DIV/0! | I9: =SUM(I6:I8) -> #DIV/0! | ... L9: =SUM(L6:L8) -> #DIV/0!

Sheet Cash Flow
B1: Year 0 | C1: Year 1 | D1: Year 2 | E1: Year 3 | F1: Year 4 | G1: Year 5 | H1: Year 6 | I1: Year 7 | J1: Year 8 | K1: Year 9 | L1: Year 10
A2: PAT | B2: ='P&L'!B10 -> #DIV/0! | C2: ='P&L'!C10 -> #DIV/0! | D2: ='P&L'!D10 -> #DIV/0! | E2: ='P&L'!E10 -> #DIV/0! | F2: ='P&L'!F10 -> #DIV/0! | G2: ='P&L'!G10 -> #DIV/0! | H2: ='P&L'!H10 -> #DIV/0! | I2: ='P&L'!I10 -> #DIV/0! | ... L2: ='P&L'!L10 -> #DIV/0!
A3: Depreciation | B3: ='P&L'!B5 -> #DIV/0! | C3: ='P&L'!C5 -> #DIV/0! | D3: ='P&L'!D5 -> #DIV/0! | E3: ='P&L'!E5 -> #DIV/0! | F3: ='P&L'!F5 -> #DIV/0! | G3: ='P&L'!G5 -> #DIV/0! | H3: ='P&L'!H5 -> #DIV/0! | I3: ='P&L'!I5 -> #DIV/0! | ... L3: ='P&L'!L5 -> #DIV/0!
A4: Change in WC
A5: Operating CF | B5: =B2+B3-B4 -> #DIV/0! | C5: =C2+C3-C4 -> #DIV/0! | D5: =D2+D3-D4 -> #DIV/0! | E5: =E2+E3-E4 -> #DIV/0! | F5: =F2+F3-F4 -> #DIV/0! | G5: =G2+G3-G4 -> #DIV/0! | H5: =H2+H3-H4 -> #DIV/0! | I5: =I2+I3-I4 -> #DIV/0! | ... L5: =L2+L3-L4 -> #DIV/0!
A6: Capex | B6: =-Assumptions!B7 -> 0 | C6: =-Assumptions!C7 -> 0 | D6: =-Assumptions!D7 -> 0 | E6: =-Assumptions!E7 -> 0 | F6: =-Assumptions!F7 -> 0 | G6: =-Assumptions!G7 -> 0 | H6: =-Assumptions!H7 -> 0 | I6: =-Assumptions!I7 -> 0 | ... L6: =-Assumptions!L7 -> 0
A7: Equity | B7: =Assumptions!B13 -> 0 | C7: =Assumptions!C13 -> 0 | D7: =Assumptions!D13 -> 0 | E7: =Assumptions!E13 -> 0 | F7: =Assumptions!F13 -> 0 | G7: =Assumptions!G13 -> 0 | H7: =Assumptions!H13 -> 0 | I7: =Assumptions!I13 -> 0 | ... L7: =Assumptions!L13 -> 0
A8: Debt | B8: =Assumptions!B14 -> 0 | C8: =Assumptions!C14 -> 0 | D8: =Assumptions!D14 -> 0 | E8: =Assumptions!E14 -> 0 | F8: =Assumptions!F14 -> 0 | G8: =Assumptions!G14 -> 0 | H8: =Assumptions!H14 -> 0 | I8: =Assumptions!I14 -> 0 | ... L8: =Assumptions!L14 -> 0
A9: Net Cash Flow | B9: =SUM(B5:B8) -> #DIV/0! | C9: =SUM(C5:C8) -> #DIV/0! | D9: =SUM(D5:D8) -> #DIV/0! | E9: =SUM(E5:E8) -> #DIV/0! | F9: =SUM(F5:F8) -> #DIV/0! | G9: =SUM(G5:G8) -> #DIV/0! | H9: =SUM(H5:H8) -> #DIV/0! | I9: =SUM(I5:I8) -> #DIV/0! | ... L9: =SUM(L5:L8) -> #DIV/0!
